pom/__init__.py
pom/base.py
pom/utils.py
pom/ui/__init__.py
pom/ui/base.py
pom/ui/button.py
pom/ui/checkbox.py
pom/ui/combobox.py
pom/ui/fields.py
pom/ui/form.py
pom/ui/link.py
pom/ui/table.py
python_pom-1.0.7.dist-info/METADATA
python_pom-1.0.7.dist-info/WHEEL
python_pom-1.0.7.dist-info/top_level.txt
python_pom-1.0.7.dist-info/RECORD
