Metadata-Version: 2.1
Name: python-pom
Version: 1.0.7
Summary: POM is Page-Object-Model microframework to develop web UI tests easy, quickly and with pleasure.
Home-page: https://github.com/sergeychipiga/pom
Author: Sergei Chipiga
Author-email: chipiga86@gmail.com
License: GPLv2
Platform: UNKNOWN
Requires-Dist: selenium (==3.141.0)
Requires-Dist: waiting (==1.4.1)
Requires-Dist: six (==1.15.0)
